{
  "fileTypes": ["js", "jsx", "ts", "tsx"],
  "injectionSelector": "L:source -comment -string",
  "patterns": [
    {
      "contentName": "source.regular.template.comment",
      "begin": "[=:]\\s*`",
      "beginCaptures": {
        "0": {
          "name": "punctuation.definition.string.template.begin.js string.template.js"
        }
      },
      "end": "`",
      "endCaptures": {
        "0": {
          "name": "punctuation.definition.string.template.end.js string.template.js"
        }
      },
      "patterns": [
        {
          "begin": "<!--\\s*@regular\\s*-->",
          "beginCaptures": {
            "0": {
              "patterns": [{ "include": "text.html.regular-html" }]
            }
          },
          "end": "(?=`)",
          "patterns": [
            {
              "include": "text.html.regular-html"
            }
          ]
        }
      ]
    },
    {
      "contentName": "source.regular.template.const",
      "begin": "(const)\\s*(\\w*[tT]pl)\\s*=\\s*(`)",
      "beginCaptures": {
        "1": {
          "patterns": [
            {
              "include": "source.ts#var-expr"
            }
          ]
        },
        "2": {
          "patterns": [
            {
              "include": "source.ts#var-single-const"
            }
          ]
        },
        "3": {
          "name": "punctuation.definition.string.template.begin.js string.template.js"
        }
      },
      "end": "`",
      "endCaptures": {
        "0": {
          "name": "punctuation.definition.string.template.end.js string.template.js"
        }
      },
      "patterns": [
        {
          "include": "text.html.regular-html"
        }
      ]
    }
  ],
  "scopeName": "regular-injection"
}
